<?xml version="1.0"?>
<opencv_storage>
<cascade>
  <stageType>BOOST</stageType>
  <featureType>HAAR</featureType>
  <height>24</height>
  <width>24</width>
  <stageParams>
    <boostType>GAB</boostType>
    <minHitRate>9.9500000476837158e-01</minHitRate>
    <maxFalseAlarm>5.0000000000000000e-01</maxFalseAlarm>
    <weightTrimRate>9.4999998807907104e-01</weightTrimRate>
    <maxDepth>1</maxDepth>
    <maxWeakCount>100</maxWeakCount></stageParams>
  <featureParams>
    <maxCatCount>0</maxCatCount>
    <featSize>1</featSize>
    <mode>BASIC</mode></featureParams>
  <stageNum>20</stageNum>
  <stages>
    <!-- stage 0 -->
    <_>
      <maxWeakCount>2</maxWeakCount>
      <stageThreshold>-3.9657909423112869e-02</stageThreshold>
      <weakClassifiers>
        <_>
          <internalNodes>
            0 -1 0 9.0272866189479828e-02</internalNodes>
          <leafValues>
            -6.9230771064758301e-01 9.3939393758773804e-01</leafValues></_>
        <_>
          <internalNodes>
            0 -1 2 2.2885951399803162e-01</internalNodes>
          <leafValues>
            6.5264976024627686e-01 -9.7455525398254395e-01</leafValues></_></weakClassifiers></_>
    <!-- stage 1 -->
    <_>
      <maxWeakCount>2</maxWeakCount>
      <stageThreshold>-4.5962402224540710e-01</stageThreshold>
      <weakClassifiers>
        <_>
          <internalNodes>
            0 -1 31 -4.8058662563562393e-02</internalNodes>
          <leafValues>
            8.0000001192092896e-01 -8.7586206197738647e-01</leafValues></_>
        <_>
          <internalNodes>
            0 -1 46 4.3347649276256561e-02</internalNodes>
          <leafValues>
            4.1623803973197937e-01 -1.</leafValues></_></weakClassifiers></_>
    <!-- stage 2 -->
    <_>
      <maxWeakCount>4</maxWeakCount>
      <stageThreshold>-1.0958472490310669e+00</stageThreshold>
      <weakClassifiers>
        <_>
          <internalNodes>
            0 -1 55 -7.6202284544706345e-03</internalNodes>
          <leafValues>
            8.0000001192092896e-01 -5.8857142925262451e-01</leafValues></_>
        <_>
          <internalNodes>
            0 -1 18 -1.7416477203369141e-01</internalNodes>
          <leafValues>
            -9.0996330976486206e-01 3.4014657139778137e-01</leafValues></_>
        <_>
          <internalNodes>
            0 -1 38 -8.5385307669639587e-02</internalNodes>
          <leafValues>
            7.3543405532836914e-01 -4.6885475516319275e-01</leafValues></_>
        <_>
          <internalNodes>
            0 -1 40 -3.6645412445068359e-02</internalNodes>
          <leafValues>
            8.8442420959472656e-01 -3.7856760621070862e-01</leafValues></_></weakClassifiers></_>
    <!-- stage 3 -->
    <_>
      <maxWeakCount>3</maxWeakCount>
      <stageThreshold>-6.9211912155151367e-01</stageThreshold>
      <weakClassifiers>
        <_>
          <internalNodes>
            0 -1 4 9.1912783682346344e-02</internalNodes>
          <leafValues>
            -5.3191488981246948e-01 9.5744681358337402e-01</leafValues></_>
        <_>
          <internalNodes>
            0 -1 16 -2.4240345228463411e-03</internalNodes>
          <leafValues>
            -9.3856900930404663e-01 4.6136882901191711e-01</leafValues></_>
        <_>
          <internalNodes>
            0 -1 49 -4.2737261392176151e-03</internalNodes>
          <leafValues>
            7.7836477756500244e-01 -5.0800377130508423e-01</leafValues></_></weakClassifiers></_>
    <!-- stage 4 -->
    <_>
      <maxWeakCount>2</maxWeakCount>
      <stageThreshold>-1.5018132328987122e-01</stageThreshold>
      <weakClassifiers>
        <_>
          <internalNodes>
            0 -1 1 2.0679214596748352e-01</internalNodes>
          <leafValues>
            -5.9116023778915405e-01 9.6296298503875732e-01</leafValues></_>
        <_>
          <internalNodes>
            0 -1 19 -9.9879354238510132e-02</internalNodes>
          <leafValues>
            -9.8445159196853638e-01 4.4097888469696045e-01</leafValues></_></weakClassifiers></_>
    <!-- stage 5 -->
    <_>
      <maxWeakCount>5</maxWeakCount>
      <stageThreshold>-3.6462640762329102e-01</stageThreshold>
      <weakClassifiers>
        <_>
          <internalNodes>
            0 -1 5 8.1063941121101379e-02</internalNodes>
          <leafValues>
            -6.0714286565780640e-01 7.0149254798889160e-01</leafValues></_>
        <_>
          <internalNodes>
            0 -1 47 -8.0582872033119202e-02</internalNodes>
          <leafValues>
            7.9492843151092529e-01 -4.6807920932769775e-01</leafValues></_>
        <_>
          <internalNodes>
            0 -1 11 1.5720229595899582e-02</internalNodes>
          <leafValues>
            -4.3074113130569458e-01 6.6345965862274170e-01</leafValues></_>
        <_>
          <internalNodes>
            0 -1 23 -7.2454498149454594e-04</internalNodes>
          <leafValues>
            4.9391511082649231e-01 -6.4859777688980103e-01</leafValues></_>
        <_>
          <internalNodes>
            0 -1 42 -3.8449240382760763e-03</internalNodes>
          <leafValues>
            7.4151152372360229e-01 -4.4677913188934326e-01</leafValues></_></weakClassifiers></_>
    <!-- stage 6 -->
    <_>
      <maxWeakCount>4</maxWeakCount>
      <stageThreshold>-4.5384311676025391e-01</stageThreshold>
      <weakClassifiers>
        <_>
          <internalNodes>
            0 -1 35 -6.5039629116654396e-03</internalNodes>
          <leafValues>
            6.8750000000000000e-01 -5.7894736528396606e-01</leafValues></_>
        <_>
          <internalNodes>
            0 -1 12 1.8348950834479183e-04</internalNodes>
          <leafValues>
            3.0026304721832275e-01 -8.5461723804473877e-01</leafValues></_>
        <_>
          <internalNodes>
            0 -1 28 1.1999672278761864e-02</internalNodes>
          <leafValues>
            -4.8646247386932373e-01 5.6253963708877563e-01</leafValues></_>
        <_>
          <internalNodes>
            0 -1 72 -1.1018796794814989e-04</internalNodes>
          <leafValues>
            -7.3769843578338623e-01 4.2080029845237732e-01</leafValues></_></weakClassifiers></_>
    <!-- stage 7 -->
    <_>
      <maxWeakCount>3</maxWeakCount>
      <stageThreshold>-4.9761188030242920e-01</stageThreshold>
      <weakClassifiers>
        <_>
          <internalNodes>
            0 -1 8 1.6167230904102325e-01</internalNodes>
          <leafValues>
            -5.7608693838119507e-01 1.</leafValues></_>
        <_>
          <internalNodes>
            0 -1 10 -1.7043284606188536e-03</internalNodes>
          <leafValues>
            -6.2723356485366821e-01 5.8884620666503906e-01</leafValues></_>
        <_>
          <internalNodes>
            0 -1 39 4.6172603964805603e-02</internalNodes>
          <leafValues>
            -5.1037114858627319e-01 8.4680843353271484e-01</leafValues></_></weakClassifiers></_>
    <!-- stage 8 -->
    <_>
      <maxWeakCount>3</maxWeakCount>
      <stageThreshold>7.1234866045415401e-03</stageThreshold>
      <weakClassifiers>
        <_>
          <internalNodes>
            0 -1 34 -1.3999998569488525e-01</internalNodes>
          <leafValues>
            7.0588237047195435e-01 -6.1676645278930664e-01</leafValues></_>
        <_>
          <internalNodes>
            0 -1 69 -7.5359822949394584e-04</internalNodes>
          <leafValues>
            -9.2431235313415527e-01 3.3402952551841736e-01</leafValues></_>
        <_>
          <internalNodes>
            0 -1 66 -8.1031757872551680e-04</internalNodes>
          <leafValues>
            -9.5273005962371826e-01 2.8986042737960815e-01</leafValues></_></weakClassifiers></_>
    <!-- stage 9 -->
    <_>
      <maxWeakCount>2</maxWeakCount>
      <stageThreshold>-2.3564355075359344e-01</stageThreshold>
      <weakClassifiers>
        <_>
          <internalNodes>
            0 -1 6 9.1040983796119690e-02</internalNodes>
          <leafValues>
            -5.3333336114883423e-01 7.4545454978942871e-01</leafValues></_>
        <_>
          <internalNodes>
            0 -1 73 6.8103359080851078e-04</internalNodes>
          <leafValues>
            3.4260794520378113e-01 -9.8109811544418335e-01</leafValues></_></weakClassifiers></_>
    <!-- stage 10 -->
    <_>
      <maxWeakCount>3</maxWeakCount>
      <stageThreshold>-6.2510657310485840e-01</stageThreshold>
      <weakClassifiers>
        <_>
          <internalNodes>
            0 -1 56 1.6865002180566080e-05</internalNodes>
          <leafValues>
            -7.7027028799057007e-01 6.7816090583801270e-01</leafValues></_>
        <_>
          <internalNodes>
            0 -1 63 1.6764577594585717e-05</internalNodes>
          <leafValues>
            -5.9323203563690186e-01 8.5248631238937378e-01</leafValues></_>
        <_>
          <internalNodes>
            0 -1 15 -4.9857200792757794e-05</internalNodes>
          <leafValues>
            7.5728946924209595e-01 -7.0732259750366211e-01</leafValues></_></weakClassifiers></_>
    <!-- stage 11 -->
    <_>
      <maxWeakCount>3</maxWeakCount>
      <stageThreshold>-4.3452084064483643e-01</stageThreshold>
      <weakClassifiers>
        <_>
          <internalNodes>
            0 -1 52 1.7072154150810093e-05</internalNodes>
          <leafValues>
            -6.4912283420562744e-01 8.7500000000000000e-01</leafValues></_>
        <_>
          <internalNodes>
            0 -1 58 1.6961061191977933e-05</internalNodes>
          <leafValues>
            -5.7692825794219971e-01 7.7615880966186523e-01</leafValues></_>
        <_>
          <internalNodes>
            0 -1 32 -1.6865002180566080e-05</internalNodes>
          <leafValues>
            7.9153025150299072e-01 -5.5831903219223022e-01</leafValues></_></weakClassifiers></_>
    <!-- stage 12 -->
    <_>
      <maxWeakCount>4</maxWeakCount>
      <stageThreshold>-6.0832995176315308e-01</stageThreshold>
      <weakClassifiers>
        <_>
          <internalNodes>
            0 -1 65 -1.5401619020849466e-04</internalNodes>
          <leafValues>
            -8.5454547405242920e-01 3.1200000643730164e-01</leafValues></_>
        <_>
          <internalNodes>
            0 -1 50 1.6891940031200647e-03</internalNodes>
          <leafValues>
            3.7151598930358887e-01 -9.1669261455535889e-01</leafValues></_>
        <_>
          <internalNodes>
            0 -1 60 -3.4265842288732529e-02</internalNodes>
          <leafValues>
            9.4184911251068115e-01 -4.9800956249237061e-01</leafValues></_>
        <_>
          <internalNodes>
            0 -1 59 6.0202786698937416e-04</internalNodes>
          <leafValues>
            4.9437218904495239e-01 -7.8168839216232300e-01</leafValues></_></weakClassifiers></_>
    <!-- stage 13 -->
    <_>
      <maxWeakCount>3</maxWeakCount>
      <stageThreshold>-6.2706869840621948e-01</stageThreshold>
      <weakClassifiers>
        <_>
          <internalNodes>
            0 -1 25 -6.1139147728681564e-02</internalNodes>
          <leafValues>
            4.3636363744735718e-01 -8.2400000095367432e-01</leafValues></_>
        <_>
          <internalNodes>
            0 -1 54 9.3441866338253021e-03</internalNodes>
          <leafValues>
            -4.4145300984382629e-01 6.5708637237548828e-01</leafValues></_>
        <_>
          <internalNodes>
            0 -1 29 9.2681437730789185e-02</internalNodes>
          <leafValues>
            -4.1887685656547546e-01 6.3838428258895874e-01</leafValues></_></weakClassifiers></_>
    <!-- stage 14 -->
    <_>
      <maxWeakCount>4</maxWeakCount>
      <stageThreshold>-6.1966991424560547e-01</stageThreshold>
      <weakClassifiers>
        <_>
          <internalNodes>
            0 -1 57 -4.5041684061288834e-02</internalNodes>
          <leafValues>
            5.4838711023330688e-01 -5.1445084810256958e-01</leafValues></_>
        <_>
          <internalNodes>
            0 -1 71 -1.7560923006385565e-03</internalNodes>
          <leafValues>
            -8.8705849647521973e-01 2.6508405804634094e-01</leafValues></_>
        <_>
          <internalNodes>
            0 -1 64 1.7184731404995546e-05</internalNodes>
          <leafValues>
            -5.3226566314697266e-01 5.0219976902008057e-01</leafValues></_>
        <_>
          <internalNodes>
            0 -1 13 5.9723085723817348e-04</internalNodes>
          <leafValues>
            2.7963966131210327e-01 -1.</leafValues></_></weakClassifiers></_>
    <!-- stage 15 -->
    <_>
      <maxWeakCount>5</maxWeakCount>
      <stageThreshold>-9.7869807481765747e-01</stageThreshold>
      <weakClassifiers>
        <_>
          <internalNodes>
            0 -1 22 -3.8054782635299489e-05</internalNodes>
          <leafValues>
            -7.8494626283645630e-01 1.2676055729389191e-01</leafValues></_>
        <_>
          <internalNodes>
            0 -1 27 -5.7338613260071725e-05</internalNodes>
          <leafValues>
            4.7318330407142639e-01 -5.1916414499282837e-01</leafValues></_>
        <_>
          <internalNodes>
            0 -1 7 5.3875789046287537e-02</internalNodes>
          <leafValues>
            -3.8344427943229675e-01 6.6832172870635986e-01</leafValues></_>
        <_>
          <internalNodes>
            0 -1 44 3.1001705792732537e-05</internalNodes>
          <leafValues>
            -4.0740919113159180e-01 6.0155564546585083e-01</leafValues></_>
        <_>
          <internalNodes>
            0 -1 67 -1.8832308705896139e-03</internalNodes>
          <leafValues>
            -8.0440586805343628e-01 3.9671313762664795e-01</leafValues></_></weakClassifiers></_>
    <!-- stage 16 -->
    <_>
      <maxWeakCount>5</maxWeakCount>
      <stageThreshold>-7.3899435997009277e-01</stageThreshold>
      <weakClassifiers>
        <_>
          <internalNodes>
            0 -1 43 3.3786469430197030e-05</internalNodes>
          <leafValues>
            -5.6790125370025635e-01 5.0684928894042969e-01</leafValues></_>
        <_>
          <internalNodes>
            0 -1 37 -1.6619065718259662e-05</internalNodes>
          <leafValues>
            6.4021092653274536e-01 -3.9735910296440125e-01</leafValues></_>
        <_>
          <internalNodes>
            0 -1 13 -1.8758838996291161e-04</internalNodes>
          <leafValues>
            -8.0221211910247803e-01 3.5953375697135925e-01</leafValues></_>
        <_>
          <internalNodes>
            0 -1 45 2.8551145805977285e-04</internalNodes>
          <leafValues>
            -4.4942882657051086e-01 5.8416962623596191e-01</leafValues></_>
        <_>
          <internalNodes>
            0 -1 62 3.0038132535992190e-05</internalNodes>
          <leafValues>
            -5.9326159954071045e-01 4.4378668069839478e-01</leafValues></_></weakClassifiers></_>
    <!-- stage 17 -->
    <_>
      <maxWeakCount>6</maxWeakCount>
      <stageThreshold>-1.0959528684616089e+00</stageThreshold>
      <weakClassifiers>
        <_>
          <internalNodes>
            0 -1 41 3.0699152499437332e-02</internalNodes>
          <leafValues>
            -4.9438202381134033e-01 5.7894736528396606e-01</leafValues></_>
        <_>
          <internalNodes>
            0 -1 17 1.2486605904996395e-02</internalNodes>
          <leafValues>
            -4.2609366774559021e-01 5.0596845149993896e-01</leafValues></_>
        <_>
          <internalNodes>
            0 -1 14 2.2288909531198442e-04</internalNodes>
          <leafValues>
            2.6059833168983459e-01 -8.8389998674392700e-01</leafValues></_>
        <_>
          <internalNodes>
            0 -1 48 2.0587272592820227e-04</internalNodes>
          <leafValues>
            -4.3946912884712219e-01 5.9721261262893677e-01</leafValues></_>
        <_>
          <internalNodes>
            0 -1 20 6.9536538794636726e-03</internalNodes>
          <leafValues>
            -3.7421539425849915e-01 7.1642822027206421e-01</leafValues></_>
        <_>
          <internalNodes>
            0 -1 68 1.4364981325343251e-04</internalNodes>
          <leafValues>
            3.7760904431343079e-01 -7.3459947109222412e-01</leafValues></_></weakClassifiers></_>
    <!-- stage 18 -->
    <_>
      <maxWeakCount>5</maxWeakCount>
      <stageThreshold>-5.8027273416519165e-01</stageThreshold>
      <weakClassifiers>
        <_>
          <internalNodes>
            0 -1 61 -2.8014993295073509e-02</internalNodes>
          <leafValues>
            6.8000000715255737e-01 -4.8108106851577759e-01</leafValues></_>
        <_>
          <internalNodes>
            0 -1 53 1.6582717653363943e-03</internalNodes>
          <leafValues>
            3.3742883801460266e-01 -7.5046879053115845e-01</leafValues></_>
        <_>
          <internalNodes>
            0 -1 33 -3.0720002541784197e-05</internalNodes>
          <leafValues>
            5.2897614240646362e-01 -4.6836423873901367e-01</leafValues></_>
        <_>
          <internalNodes>
            0 -1 26 -7.3806091677397490e-05</internalNodes>
          <leafValues>
            4.0135765075683594e-01 -5.5970406532287598e-01</leafValues></_>
        <_>
          <internalNodes>
            0 -1 3 -6.6707248333841562e-04</internalNodes>
          <leafValues>
            7.6062369346618652e-01 -3.6961391568183899e-01</leafValues></_></weakClassifiers></_>
    <!-- stage 19 -->
    <_>
      <maxWeakCount>7</maxWeakCount>
      <stageThreshold>-1.1634507179260254e+00</stageThreshold>
      <weakClassifiers>
        <_>
          <internalNodes>
            0 -1 36 9.1985855251550674e-03</internalNodes>
          <leafValues>
            -4.3915343284606934e-01 6.0869562625885010e-01</leafValues></_>
        <_>
          <internalNodes>
            0 -1 70 -4.4273278035689145e-05</internalNodes>
          <leafValues>
            -7.4987518787384033e-01 2.5309431552886963e-01</leafValues></_>
        <_>
          <internalNodes>
            0 -1 24 3.1942225177772343e-05</internalNodes>
          <leafValues>
            -4.3577879667282104e-01 4.5522916316986084e-01</leafValues></_>
        <_>
          <internalNodes>
            0 -1 21 -1.1929974425584078e-03</internalNodes>
          <leafValues>
            -8.2999521493911743e-01 3.1558361649513245e-01</leafValues></_>
        <_>
          <internalNodes>
            0 -1 51 1.3371837849263102e-04</internalNodes>
          <leafValues>
            -6.1887979507446289e-01 4.5822519063949585e-01</leafValues></_>
        <_>
          <internalNodes>
            0 -1 30 2.6296253781765699e-03</internalNodes>
          <leafValues>
            -4.4182491302490234e-01 5.3345787525177002e-01</leafValues></_>
        <_>
          <internalNodes>
            0 -1 9 6.7982205655425787e-04</internalNodes>
          <leafValues>
            2.3119501769542694e-01 -1.</leafValues></_></weakClassifiers></_></stages>
  <features>
    <_>
      <rects>
        <_>
          0 0 24 14 -1.</_>
        <_>
          8 0 8 14 3.</_></rects>
      <tilted>0</tilted></_>
    <_>
      <rects>
        <_>
          0 0 24 19 -1.</_>
        <_>
          8 0 8 19 3.</_></rects>
      <tilted>0</tilted></_>
    <_>
      <rects>
        <_>
          0 0 21 20 -1.</_>
        <_>
          0 10 21 10 2.</_></rects>
      <tilted>0</tilted></_>
    <_>
      <rects>
        <_>
          0 2 6 1 -1.</_>
        <_>
          3 2 3 1 2.</_></rects>
      <tilted>0</tilted></_>
    <_>
      <rects>
        <_>
          0 3 10 14 -1.</_>
        <_>
          5 3 5 14 2.</_></rects>
      <tilted>0</tilted></_>
    <_>
      <rects>
        <_>
          0 5 24 6 -1.</_>
        <_>
          8 5 8 6 3.</_></rects>
      <tilted>0</tilted></_>
    <_>
      <rects>
        <_>
          0 6 18 10 -1.</_>
        <_>
          6 6 6 10 3.</_></rects>
      <tilted>0</tilted></_>
    <_>
      <rects>
        <_>
          0 7 8 15 -1.</_>
        <_>
          4 7 4 15 2.</_></rects>
      <tilted>0</tilted></_>
    <_>
      <rects>
        <_>
          0 8 24 11 -1.</_>
        <_>
          8 8 8 11 3.</_></rects>
      <tilted>0</tilted></_>
    <_>
      <rects>
        <_>
          0 11 2 2 -1.</_>
        <_>
          0 11 1 1 2.</_>
        <_>
          1 12 1 1 2.</_></rects>
      <tilted>0</tilted></_>
    <_>
      <rects>
        <_>
          0 14 3 4 -1.</_>
        <_>
          0 16 3 2 2.</_></rects>
      <tilted>0</tilted></_>
    <_>
      <rects>
        <_>
          0 15 10 5 -1.</_>
        <_>
          5 15 5 5 2.</_></rects>
      <tilted>0</tilted></_>
    <_>
      <rects>
        <_>
          0 20 2 4 -1.</_>
        <_>
          0 20 1 2 2.</_>
        <_>
          1 22 1 2 2.</_></rects>
      <tilted>0</tilted></_>
    <_>
      <rects>
        <_>
          0 22 2 2 -1.</_>
        <_>
          0 23 2 1 2.</_></rects>
      <tilted>0</tilted></_>
    <_>
      <rects>
        <_>
          0 23 4 1 -1.</_>
        <_>
          2 23 2 1 2.</_></rects>
      <tilted>0</tilted></_>
    <_>
      <rects>
        <_>
          0 23 6 1 -1.</_>
        <_>
          3 23 3 1 2.</_></rects>
      <tilted>0</tilted></_>
    <_>
      <rects>
        <_>
          1 0 7 2 -1.</_>
        <_>
          1 1 7 1 2.</_></rects>
      <tilted>0</tilted></_>
    <_>
      <rects>
        <_>
          1 0 8 12 -1.</_>
        <_>
          1 4 8 4 3.</_></rects>
      <tilted>0</tilted></_>
    <_>
      <rects>
        <_>
          1 0 23 18 -1.</_>
        <_>
          1 9 23 9 2.</_></rects>
      <tilted>0</tilted></_>
    <_>
      <rects>
        <_>
          1 1 22 12 -1.</_>
        <_>
          1 5 22 4 3.</_></rects>
      <tilted>0</tilted></_>
    <_>
      <rects>
        <_>
          1 10 9 5 -1.</_>
        <_>
          4 10 3 5 3.</_></rects>
      <tilted>0</tilted></_>
    <_>
      <rects>
        <_>
          1 21 2 3 -1.</_>
        <_>
          2 21 1 3 2.</_></rects>
      <tilted>0</tilted></_>
    <_>
      <rects>
        <_>
          1 22 1 2 -1.</_>
        <_>
          1 23 1 1 2.</_></rects>
      <tilted>0</tilted></_>
    <_>
      <rects>
        <_>
          1 23 21 1 -1.</_>
        <_>
          8 23 7 1 3.</_></rects>
      <tilted>0</tilted></_>
    <_>
      <rects>
        <_>
          2 1 2 4 -1.</_>
        <_>
          2 1 1 2 2.</_>
        <_>
          3 3 1 2 2.</_></rects>
      <tilted>0</tilted></_>
    <_>
      <rects>
        <_>
          2 14 21 10 -1.</_>
        <_>
          2 19 21 5 2.</_></rects>
      <tilted>0</tilted></_>
    <_>
      <rects>
        <_>
          2 22 4 1 -1.</_>
        <_>
          4 22 2 1 2.</_></rects>
      <tilted>0</tilted></_>
    <_>
      <rects>
        <_>
          3 20 2 2 -1.</_>
        <_>
          4 20 1 2 2.</_></rects>
      <tilted>0</tilted></_>
    <_>
      <rects>
        <_>
          4 0 11 6 -1.</_>
        <_>
          4 3 11 3 2.</_></rects>
      <tilted>0</tilted></_>
    <_>
      <rects>
        <_>
          4 1 10 21 -1.</_>
        <_>
          4 8 10 7 3.</_></rects>
      <tilted>0</tilted></_>
    <_>
      <rects>
        <_>
          4 14 6 9 -1.</_>
        <_>
          6 14 2 9 3.</_></rects>
      <tilted>0</tilted></_>
    <_>
      <rects>
        <_>
          4 14 16 10 -1.</_>
        <_>
          4 19 16 5 2.</_></rects>
      <tilted>0</tilted></_>
    <_>
      <rects>
        <_>
          5 22 2 1 -1.</_>
        <_>
          6 22 1 1 2.</_></rects>
      <tilted>0</tilted></_>
    <_>
      <rects>
        <_>
          5 23 2 1 -1.</_>
        <_>
          6 23 1 1 2.</_></rects>
      <tilted>0</tilted></_>
    <_>
      <rects>
        <_>
          6 12 13 12 -1.</_>
        <_>
          6 18 13 6 2.</_></rects>
      <tilted>0</tilted></_>
    <_>
      <rects>
        <_>
          7 18 12 2 -1.</_>
        <_>
          7 19 12 1 2.</_></rects>
      <tilted>0</tilted></_>
    <_>
      <rects>
        <_>
          8 0 2 6 -1.</_>
        <_>
          8 3 2 3 2.</_></rects>
      <tilted>0</tilted></_>
    <_>
      <rects>
        <_>
          8 10 2 3 -1.</_>
        <_>
          9 10 1 3 2.</_></rects>
      <tilted>0</tilted></_>
    <_>
      <rects>
        <_>
          8 13 9 10 -1.</_>
        <_>
          8 18 9 5 2.</_></rects>
      <tilted>0</tilted></_>
    <_>
      <rects>
        <_>
          9 1 12 20 -1.</_>
        <_>
          15 1 6 20 2.</_></rects>
      <tilted>0</tilted></_>
    <_>
      <rects>
        <_>
          9 3 12 8 -1.</_>
        <_>
          13 3 4 8 3.</_></rects>
      <tilted>0</tilted></_>
    <_>
      <rects>
        <_>
          9 15 14 8 -1.</_>
        <_>
          9 15 7 4 2.</_>
        <_>
          16 19 7 4 2.</_></rects>
      <tilted>0</tilted></_>
    <_>
      <rects>
        <_>
          9 17 10 2 -1.</_>
        <_>
          9 18 10 1 2.</_></rects>
      <tilted>0</tilted></_>
    <_>
      <rects>
        <_>
          9 21 1 2 -1.</_>
        <_>
          9 22 1 1 2.</_></rects>
      <tilted>0</tilted></_>
    <_>
      <rects>
        <_>
          10 21 1 2 -1.</_>
        <_>
          10 22 1 1 2.</_></rects>
      <tilted>0</tilted></_>
    <_>
      <rects>
        <_>
          11 9 2 12 -1.</_>
        <_>
          11 9 1 6 2.</_>
        <_>
          12 15 1 6 2.</_></rects>
      <tilted>0</tilted></_>
    <_>
      <rects>
        <_>
          11 10 12 14 -1.</_>
        <_>
          11 17 12 7 2.</_></rects>
      <tilted>0</tilted></_>
    <_>
      <rects>
        <_>
          12 12 7 12 -1.</_>
        <_>
          12 18 7 6 2.</_></rects>
      <tilted>0</tilted></_>
    <_>
      <rects>
        <_>
          13 11 2 2 -1.</_>
        <_>
          14 11 1 2 2.</_></rects>
      <tilted>0</tilted></_>
    <_>
      <rects>
        <_>
          14 16 10 1 -1.</_>
        <_>
          19 16 5 1 2.</_></rects>
      <tilted>0</tilted></_>
    <_>
      <rects>
        <_>
          14 22 3 2 -1.</_>
        <_>
          15 22 1 2 3.</_></rects>
      <tilted>0</tilted></_>
    <_>
      <rects>
        <_>
          14 22 4 2 -1.</_>
        <_>
          16 22 2 2 2.</_></rects>
      <tilted>0</tilted></_>
    <_>
      <rects>
        <_>
          14 23 2 1 -1.</_>
        <_>
          15 23 1 1 2.</_></rects>
      <tilted>0</tilted></_>
    <_>
      <rects>
        <_>
          14 23 9 1 -1.</_>
        <_>
          17 23 3 1 3.</_></rects>
      <tilted>0</tilted></_>
    <_>
      <rects>
        <_>
          16 9 6 7 -1.</_>
        <_>
          18 9 2 7 3.</_></rects>
      <tilted>0</tilted></_>
    <_>
      <rects>
        <_>
          16 9 8 2 -1.</_>
        <_>
          20 9 4 2 2.</_></rects>
      <tilted>0</tilted></_>
    <_>
      <rects>
        <_>
          16 22 4 1 -1.</_>
        <_>
          18 22 2 1 2.</_></rects>
      <tilted>0</tilted></_>
    <_>
      <rects>
        <_>
          17 4 6 18 -1.</_>
        <_>
          20 4 3 18 2.</_></rects>
      <tilted>0</tilted></_>
    <_>
      <rects>
        <_>
          17 19 2 1 -1.</_>
        <_>
          18 19 1 1 2.</_></rects>
      <tilted>0</tilted></_>
    <_>
      <rects>
        <_>
          17 21 2 3 -1.</_>
        <_>
          17 22 2 1 3.</_></rects>
      <tilted>0</tilted></_>
    <_>
      <rects>
        <_>
          18 1 6 20 -1.</_>
        <_>
          21 1 3 20 2.</_></rects>
      <tilted>0</tilted></_>
    <_>
      <rects>
        <_>
          18 8 6 7 -1.</_>
        <_>
          21 8 3 7 2.</_></rects>
      <tilted>0</tilted></_>
    <_>
      <rects>
        <_>
          18 21 2 2 -1.</_>
        <_>
          19 21 1 2 2.</_></rects>
      <tilted>0</tilted></_>
    <_>
      <rects>
        <_>
          20 21 2 1 -1.</_>
        <_>
          21 21 1 1 2.</_></rects>
      <tilted>0</tilted></_>
    <_>
      <rects>
        <_>
          20 22 2 1 -1.</_>
        <_>
          21 22 1 1 2.</_></rects>
      <tilted>0</tilted></_>
    <_>
      <rects>
        <_>
          20 22 2 2 -1.</_>
        <_>
          20 22 1 1 2.</_>
        <_>
          21 23 1 1 2.</_></rects>
      <tilted>0</tilted></_>
    <_>
      <rects>
        <_>
          21 0 2 2 -1.</_>
        <_>
          21 1 2 1 2.</_></rects>
      <tilted>0</tilted></_>
    <_>
      <rects>
        <_>
          21 11 2 6 -1.</_>
        <_>
          21 13 2 2 3.</_></rects>
      <tilted>0</tilted></_>
    <_>
      <rects>
        <_>
          22 12 1 3 -1.</_>
        <_>
          22 13 1 1 3.</_></rects>
      <tilted>0</tilted></_>
    <_>
      <rects>
        <_>
          22 15 2 3 -1.</_>
        <_>
          22 16 2 1 3.</_></rects>
      <tilted>0</tilted></_>
    <_>
      <rects>
        <_>
          22 22 2 1 -1.</_>
        <_>
          23 22 1 1 2.</_></rects>
      <tilted>0</tilted></_>
    <_>
      <rects>
        <_>
          23 6 1 9 -1.</_>
        <_>
          23 9 1 3 3.</_></rects>
      <tilted>0</tilted></_>
    <_>
      <rects>
        <_>
          23 12 1 2 -1.</_>
        <_>
          23 13 1 1 2.</_></rects>
      <tilted>0</tilted></_>
    <_>
      <rects>
        <_>
          23 15 1 3 -1.</_>
        <_>
          23 16 1 1 3.</_></rects>
      <tilted>0</tilted></_></features></cascade>
</opencv_storage>
